EnergyOffshore/EnergyOffshore_analysis_and_visualization.py
EnergyOffshore/__init__.py
energyoffshore-0.3.0.dist-info/METADATA
energyoffshore-0.3.0.dist-info/WHEEL
energyoffshore-0.3.0.dist-info/licenses/LICENCE
energyoffshore-0.3.0.dist-info/RECORD
