Metadata-Version: 2.4
Name: EnergyOffshore
Version: 0.3.0
Summary: DT Climate Energy Offshore use case
Project-URL: Homepage, https://github.com/AleksiNummelin/EnergyOffshore
Author-email: Aleksi Nummelin <aleksi.nummelin@fmi.fi>, Jonni Lehtiranta <jonni.lehtiranta@fmi.fi>, Andrew Twelves <andrew.twelves@fmi.fi>
License-File: LICENCE
Classifier: License :: OSI Approved :: MIT License
Classifier: Operating System :: OS Independent
Classifier: Programming Language :: Python :: 3
Requires-Python: >=3.8
Requires-Dist: cartopy>=0.22.0
Requires-Dist: dask>=2024.1.1
Requires-Dist: distributed>=2024.1.1
Requires-Dist: matplotlib>=3.8
Requires-Dist: numpy>=1.26.3
Requires-Dist: xarray>=2024.1.1
